psx/__init__.py
psx/web.py
psx_data_reader-0.0.6.dist-info/LICENSE
psx_data_reader-0.0.6.dist-info/METADATA
psx_data_reader-0.0.6.dist-info/WHEEL
psx_data_reader-0.0.6.dist-info/top_level.txt
psx_data_reader-0.0.6.dist-info/RECORD
