Metadata-Version: 2.1
Name: psx-data-reader
Version: 0.0.6
Summary: Pakistan Stock Exchange's Data Downloader
Home-page: https://github.com/MuhammadAmir5670/psx-data-reader
Download-URL: https://github.com/MuhammadAmir5670/psx-data-reader/archive/refs/tags/0.0.1.tar.gz
Author: Muhammad Amir Abbasi
Author-email: muhammadamir5670@gmail.com
License: MIT
Keywords: psx,Pakistan stock exchange,stocks data downloader,Pakistan stock exchange data
Platform: UNKNOWN
Classifier: Development Status :: 3 - Alpha
Classifier: Intended Audience :: Developers
Classifier: Topic :: Software Development :: Build Tools
Classifier: License :: OSI Approved :: MIT License
Classifier: Programming Language :: Python :: 3
Classifier: Programming Language :: Python :: 3.4
Classifier: Programming Language :: Python :: 3.5
Classifier: Programming Language :: Python :: 3.6
Classifier: Operating System :: OS Independent
Requires-Python: >=3
License-File: LICENSE
